airflow_parse.py
bench_db_utils.py
dag_parse.py
airflow_parse_bench-1.0.1.dist-info/LICENSE.txt
airflow_parse_bench-1.0.1.dist-info/METADATA
airflow_parse_bench-1.0.1.dist-info/WHEEL
airflow_parse_bench-1.0.1.dist-info/entry_points.txt
airflow_parse_bench-1.0.1.dist-info/top_level.txt
airflow_parse_bench-1.0.1.dist-info/RECORD
